{"lastUsed":1664344829266,"path":"C:\/WebStudy","projectCount":2,"recentFiles":[{"path":"\/WebApp02\/WebContent","parentWorkspace":"C:\/WebStudy","name":"Test002.html"},{"path":"\/WebApp02\/WebContent","parentWorkspace":"C:\/WebStudy","name":"Test001.html"},{"path":"\/WebApp02\/WebContent","parentWorkspace":"C:\/WebStudy","name":"Test019.html","lastModified":1664344833148,"locationURI":"file:\/C:\/WebStudy\/WebApp02\/WebContent\/Test019.html"},{"path":"\/WebApp02\/WebContent","parentWorkspace":"C:\/WebStudy","name":"Test018.html","lastModified":1664342796577},{"path":"\/WebApp02\/WebContent","parentWorkspace":"C:\/WebStudy","name":"Test017.html"},{"path":"\/WebApp02\/WebContent\/CSS","parentWorkspace":"C:\/WebStudy","name":"externalColor.css","lastModified":1664343377626,"locationURI":"file:\/C:\/WebStudy\/WebApp02\/WebContent\/CSS\/externalColor.css"},{"path":"\/WebApp02\/WebContent","parentWorkspace":"C:\/WebStudy","name":"Test016.html"},{"path":"\/WebApp02\/WebContent","parentWorkspace":"C:\/WebStudy","name":"Test015.html"},{"path":"\/WebApp02\/WebContent\/CSS","parentWorkspace":"C:\/WebStudy","name":"externalLink.css"},{"path":"\/WebApp02\/WebContent","parentWorkspace":"C:\/WebStudy","name":"Test014.html"},{"path":"\/WebApp02\/WebContent","parentWorkspace":"C:\/WebStudy","name":"Test009.html"},{"path":"\/WebApp02\/WebContent","parentWorkspace":"C:\/WebStudy","name":"Test013.html"},{"path":"\/WebApp02\/WebContent","parentWorkspace":"C:\/WebStudy","name":"Test008.html"},{"path":"\/WebApp02\/WebContent","parentWorkspace":"C:\/WebStudy","name":"Test012.html"},{"path":"\/WebApp02\/WebContent\/CSS","parentWorkspace":"C:\/WebStudy","name":"externalimport.css"},{"path":"\/WebApp02\/WebContent","parentWorkspace":"C:\/WebStudy","name":"Test007.html"},{"path":"\/WebApp02\/WebContent","parentWorkspace":"C:\/WebStudy","name":"Test011.html"},{"path":"\/WebApp02\/WebContent","parentWorkspace":"C:\/WebStudy","name":"Test006.html"},{"path":"\/WebApp02\/WebContent","parentWorkspace":"C:\/WebStudy","name":"Test010.html"},{"path":"\/WebApp02\/WebContent","parentWorkspace":"C:\/WebStudy","name":"Test005.html"},{"path":"\/WebApp02\/WebContent","parentWorkspace":"C:\/WebStudy","name":"Test004.html"},{"path":"\/WebApp02\/WebContent","parentWorkspace":"C:\/WebStudy","name":"Test003.html"}]}